AUTHORS
LICENSE
MANIFEST.in
README.rst
setup.cfg
setup.py
db_tools/__init__.py
db_tools/middleware.py
django_db_tools.egg-info/PKG-INFO
django_db_tools.egg-info/SOURCES.txt
django_db_tools.egg-info/dependency_links.txt
django_db_tools.egg-info/not-zip-safe
django_db_tools.egg-info/top_level.txt