Metadata-Version: 1.0
Name: django-db-tools
Version: 0.0.1
Summary: A read only mode tool for your database
Home-page: https://github.com/craigkerstiens/django-db-tools
Author: Craig Kerstiens
Author-email: craig.kerstiens@gmail.com
License: BSD
Platform: UNKNOWN
Classifier: Development Status :: 4 - Beta
Classifier: Environment :: Web Environment
Classifier: Framework :: Django
Classifier: Intended Audience :: Developers
Classifier: License :: OSI Approved :: BSD License
Classifier: Operating System :: OS Independent
Classifier: Programming Language :: Python
Classifier: Topic :: Software Development :: Libraries :: Python Modules
